simpleboxpacking.py
simpleboxpacking-0.0.2.dist-info/LICENSE
simpleboxpacking-0.0.2.dist-info/METADATA
simpleboxpacking-0.0.2.dist-info/WHEEL
simpleboxpacking-0.0.2.dist-info/top_level.txt
simpleboxpacking-0.0.2.dist-info/RECORD
