Metadata-Version: 2.1
Name: simpleboxpacking
Version: 0.0.2
Summary: Put n same size boxes into a rectangle.
Home-page: UNKNOWN
Author: Summer Fang
License: UNKNOWN
Platform: UNKNOWN
Classifier: Programming Language :: Python :: 3
Classifier: License :: OSI Approved :: MIT License
Classifier: Operating System :: OS Independent
Requires-Python: >=3.5
